napari_tardis_em/__init__.py
napari_tardis_em/_version.py
napari_tardis_em/napari.yaml
napari_tardis_em/readers/__init__.py
napari_tardis_em/readers/import_data.py
napari_tardis_em/utils/__init__.py
napari_tardis_em/utils/export_coord.py
napari_tardis_em/utils/export_image.py
napari_tardis_em/utils/import_data.py
napari_tardis_em/utils/utils.py
napari_tardis_em/viewers/__init__.py
napari_tardis_em/viewers/styles.py
napari_tardis_em/viewers/utils.py
napari_tardis_em/viewers/viewer_actin_3d.py
napari_tardis_em/viewers/viewer_analysis_tirf.py
napari_tardis_em/viewers/viewer_fiber_analysis.py
napari_tardis_em/viewers/viewer_fiber_edit.py
napari_tardis_em/viewers/viewer_mem_2d.py
napari_tardis_em/viewers/viewer_mem_3d.py
napari_tardis_em/viewers/viewer_mt_2d.py
napari_tardis_em/viewers/viewer_mt_3d.py
napari_tardis_em/viewers/viewer_mt_tirf.py
napari_tardis_em/viewers/viewer_predict.py
napari_tardis_em/viewers/viewer_train.py
napari_tardis_em/viewers/viewer_utils.py
napari_tardis_em-0.3.23.dist-info/licenses/LICENSE
napari_tardis_em-0.3.23.dist-info/METADATA
napari_tardis_em-0.3.23.dist-info/WHEEL
napari_tardis_em-0.3.23.dist-info/entry_points.txt
napari_tardis_em-0.3.23.dist-info/top_level.txt
napari_tardis_em-0.3.23.dist-info/RECORD
