Metadata-Version: 2.4
Name: napari-tardis-em
Version: 0.3.23
Summary: Tomogram and micrograph segmentation with TARDIS-em
Home-page: https://github.com/SMLC-NYSBC/napari-tardis_em
Author: Robert Kiewisz
Author-email: robert.kiewisz@gmail.com, rkiewisz@nysbc.org
License: MIT
Classifier: Development Status :: 5 - Production/Stable
Classifier: Framework :: napari
Classifier: Intended Audience :: Developers
Classifier: Operating System :: OS Independent
Classifier: Programming Language :: Python :: 3.10
Classifier: Topic :: Scientific/Engineering :: Image Processing
Requires-Python: >=3.10
License-File: LICENSE
Requires-Dist: setuptools>=70.3.0
Requires-Dist: napari>=0.5.0
Requires-Dist: torch>=2.2.2
Requires-Dist: tardis_em[nd2]==0.3.22
Requires-Dist: tardis_em_analysis==0.3.22
Requires-Dist: numpy>=2.0.0
Requires-Dist: matplotlib>=3.9.1
Requires-Dist: qtpy>=2.4.1
Requires-Dist: pyqt5>=5.15.10
Requires-Dist: opencv-python
Provides-Extra: testing
Requires-Dist: tox; extra == "testing"
Requires-Dist: pytest; extra == "testing"
Requires-Dist: pytest-cov; extra == "testing"
Requires-Dist: pytest-qt; extra == "testing"
Requires-Dist: napari; extra == "testing"
Requires-Dist: pyqt5; extra == "testing"
Dynamic: license-file
